structured_data_validation/.idea/inspectionProfiles/Project_Default.xml
structured_data_validation/.idea/inspectionProfiles/profiles_settings.xml
structured_data_validation/.idea/modules.xml
structured_data_validation/.idea/structured_data_validation.iml
structured_data_validation/.idea/vcs.xml
structured_data_validation/.idea/workspace.xml
structured_data_validation/__init__.py
structured_data_validation/conf/__init__.py
structured_data_validation/conf/config.py
structured_data_validation/database/__init__.py
structured_data_validation/logger.py
structured_data_validation/logging/__init__.py
structured_data_validation/logging/decorators.py
structured_data_validation/logging/formatter.py
structured_data_validation/logging/gcp_logger.py
structured_data_validation/logging/handler.py
structured_data_validation/models/AROS.py
structured_data_validation/models/AROS_entities.py
structured_data_validation/models/MPFC.py
structured_data_validation/models/MPSC.py
structured_data_validation/models/SPFC.py
structured_data_validation/models/SPSC.py
structured_data_validation/models/__init__.py
structured_data_validation/models/base.py
structured_data_validation/models/datatypes.py
structured_data_validation/models/validate.py
structured_data_validation/scripts/__init__.py
structured_data_validation/scripts/cloud_messages.py
structured_data_validation/scripts/conf.py
structured_data_validation/scripts/validate_file.py
structured_data_validation/utils/__init__.py
structured_data_validation/utils/models_factory.py
structured_data_validation/utils/models_importer.py
structured_data_validation-0.1.2.dist-info/entry_points.txt
structured_data_validation-0.1.2.dist-info/LICENSE
structured_data_validation-0.1.2.dist-info/LICENSE.txt
structured_data_validation-0.1.2.dist-info/WHEEL
structured_data_validation-0.1.2.dist-info/METADATA
structured_data_validation-0.1.2.dist-info/RECORD
